[{"qInfo":{"qId":"ba2dafcc-5e03-4b82-8696-6bff078bba99","qType":"bookmark"},"qMeta":{"title":"Bookmark 1","description":"","createdDate":"2024-05-07T06:59:58.472Z","modifiedDate":"2024-05-07T06:59:58.472Z","published":false,"publishTime":"1753-01-01T00:00:00.000Z","approved":false,"owner":{"id":"5d9d879d-fa4b-4922-8e8d-2abeb791ca6e","userId":"rajasekarv","userDirectory":"GAIN-INSIGHTS","userDirectoryConnectorName":"","name":"rajasekarv","privileges":null},"qSize":-1,"sourceObject":"","draftObject":"","privileges":["read","update","delete","exportdata","publish","approve"],"isExtended":false},"qData":{"qBookmark":{"qStateData":[{"qStateName":"$","qFieldItems":[{"qDef":{"qName":"City","qType":"PRESENT"},"qSelectInfo":{"qRangeLo":"NaN","qRangeHi":"NaN","qNumberFormat":{"qType":"U","qnDec":10,"qUseThou":0},"qRangeInfo":[],"qContinuousRangeInfo":[]},"qValues":[],"qExcludedValues":[]},{"qDef":{"qName":"Date","qType":"PRESENT"},"qSelectInfo":{"qRangeLo":"NaN","qRangeHi":"NaN","qNumberFormat":{"qType":"U","qnDec":10,"qUseThou":0},"qRangeInfo":[],"qContinuousRangeInfo":[]},"qValues":[],"qExcludedValues":[]},{"qDef":{"qName":"Payment","qType":"PRESENT"},"qSelectInfo":{"qRangeLo":"NaN","qRangeHi":"NaN","qNumberFormat":{"qType":"U","qnDec":10,"qUseThou":0},"qRangeInfo":[],"qContinuousRangeInfo":[]},"qValues":[],"qExcludedValues":[]}]},{"qStateName":"alter 3","qFieldItems":[]},{"qStateName":"alter 2","qFieldItems":[]},{"qStateName":"alter 1","qFieldItems":[]}],"qUtcModifyTime":45420.50315972222,"qVariableItems":[],"qPatches":[]},"qSheetId":"f811ea4a-a808-4354-862e-2114db77ede2","qExpression":"<City={'Yangon','Mandalay'},Date={'01/01/2019','03/01/2019','06/01/2019','02/02/2019'},Payment={'Cash','Ewallet'}>"}}]