{"jsonrpc":"2.0","id":0,"result":{"qPropEntry":{"qProperty":{"qInfo":{"qId":"12a149ba-d340-4583-9439-fca9679dfb6e","qType":"sheet"},"qMetaDef":{"title":"Writeback with S3 Bucket","description":""},"rank":14,"thumbnail":{"qStaticContentUrlDef":{"qUrl":"/appcontent/6ec03432-2f6c-4811-9fac-ccbc3d2cd311/s3-logs-cover.jpg"}},"columns":36,"rows":18,"cells":[{"name":"dNKAPs","type":"SenseOpsSheetMenu","col":29,"row":16,"colspan":7,"rowspan":2,"bounds":{"y":88.88888888888889,"x":80.55555555555556,"width":19.444444444444446,"height":11.11111111111111}},{"name":"ZxJHHQm","type":"SenseOpsWriteback","col":0,"row":0,"colspan":20,"rowspan":18,"bounds":{"y":0,"x":0,"width":55.55555555555556,"height":100}}],"qChildListDef":{"qData":{"title":"/title"}},"gridResolution":"large","layoutOptions":{"mobileLayout":"LIST"},"gridMode":"edit","customRowBase":24},"qChildren":[{"qProperty":{"qInfo":{"qId":"dNKAPs","qType":"SenseOpsSheetMenu"},"qExtendsId":"cd8e6045-43b3-4d33-bc7f-3a6fe242005b","qMetaDef":{}},"qChildren":[]},{"qProperty":{"qInfo":{"qId":"ZxJHHQm","qType":"SenseOpsWriteback"},"qMetaDef":{},"qHyperCubeDef":{"qDimensions":[{"qDef":{"qGrouping":"N","qFieldDefs":["BrandBranchMonthKey"],"qFieldLabels":[],"qSortCriterias":[{"qSortByNumeric":1,"qSortByAscii":1,"qSortByLoadOrder":1,"qExpression":{}}],"qNumberPresentations":[],"qActiveField":0,"autoSort":false,"cId":"yydQUV","numFormatFromTemplate":true,"columnType":"text","showOptions":false,"options":{"defineOptions":true,"customOptions":[],"field":"","useAssociatedFields":false,"associatedGroup":"Group01","hasLinked":false,"linkedField":"","linkedFieldIndex":0,"paddingBtw":10},"refName":"BrandBranchMonthKey","showColumn":1,"showsearch":true,"style":{"width":200,"wrapText":false,"textAlign":"start","fontWeight":"inherit","headerBgColor":"","headerFontColor":"","headerIcon":{"show":false,"type":"solid","name":"faIcons","position":"left","alignhdr":false,"showLabel":true,"size":13,"color":{"color":"#595959","index":"-1"}}}},"qNullSuppression":true,"qOtherTotalSpec":{"qOtherMode":"OTHER_OFF","qOtherCounted":{"qv":"10"},"qOtherLimit":{},"qOtherLimitMode":"OTHER_GT_LIMIT","qForceBadValueKeeping":true,"qApplyEvenWhenPossiblyWrongResult":true,"qOtherSortMode":"OTHER_SORT_DESCENDING","qTotalMode":"TOTAL_OFF","qReferencedExpression":{}},"qOtherLabel":{},"qTotalLabel":{},"qCalcCond":{},"qAttributeExpressions":[{"qExpression":"0","qAttribute":true},{"qAttribute":true},{"qAttribute":true},{"qAttribute":true}],"qAttributeDimensions":[],"qCalcCondition":{"qCond":{},"qMsg":{}}}],"qMeasures":[{"qDef":{"qLabel":"inputData","qTags":[],"qGrouping":"N","qDef":"[inputData]","qAccumulate":0,"qActiveExpression":0,"qExpressions":[],"autoSort":false,"cId":"fMidPh","numFormatFromTemplate":true,"columnType":"text","isColumnEditable":1,"text":{"dataType":"text","hideEditIcon":false,"placeholder":""},"refName":"inputData","showOptions":false,"options":{"defineOptions":true,"customOptions":[{"value":"Option1","cId":"MwhLme"},{"value":"Option2","cId":"RwDdJJ"}],"field":"","useAssociatedFields":false,"associatedGroup":"Group01","hasLinked":false,"linkedField":"","linkedFieldIndex":0,"paddingBtw":10},"dropdown":{"hideDDIcon":false},"checkbox":{"color":{"color":"#1976d2","index":"-1"},"multiChoice":false,"isSwitch":false,"isCustomValue":false,"checkedValue":"1","unCheckedValue":"0","disabledFill":"#767676"},"radio":{"color":{"color":"#1976d2","index":"-1"}},"slider":{"isDefault":false,"showLabel":true,"inputWidth":25,"color":{"color":"#1976d2","index":"-1"},"minValue":0,"maxValue":100,"size":1},"rating":{"count":5,"emptyColor":"","size":21},"colorpicker":{"isRound":false},"showColumn":1,"style":{"width":200,"wrapText":false,"textAlign":"start","fontWeight":"inherit","headerBgColor":"","headerFontColor":"","headerIcon":{"show":false,"type":"solid","name":"faIcons","position":"left","alignhdr":false,"showLabel":true,"size":13,"color":{"color":"#595959","index":"-1"}}}},"qSortBy":{"qExpression":{}},"qAttributeExpressions":[{"qExpression":"0","qAttribute":true},{"qAttribute":true},{"qAttribute":true},{"qAttribute":true}],"qAttributeDimensions":[],"qCalcCond":{},"qCalcCondition":{"qCond":{},"qMsg":{}},"qTrendLines":[],"qMiniChartDef":{"qSortBy":{"qExpression":{}},"qOtherTotalSpec":{"qOtherMode":"OTHER_OFF","qOtherCounted":{},"qOtherLimit":{},"qOtherLimitMode":"OTHER_GT_LIMIT","qForceBadValueKeeping":true,"qApplyEvenWhenPossiblyWrongResult":true,"qOtherSortMode":"OTHER_SORT_DESCENDING","qTotalMode":"TOTAL_OFF","qReferencedExpression":{}},"qMaxNumberPoints":-1,"qAttributeExpressions":[]}}],"qInterColumnSortOrder":[0,1],"qInitialDataFetch":[{"qLeft":0,"qTop":0,"qWidth":100,"qHeight":100}],"qReductionMode":"N","qMode":"S","qPseudoDimPos":-1,"qNoOfLeftDims":-1,"qMaxStackedCells":5000,"qCalcCond":{},"qTitle":{},"qCalcCondition":{"qCond":{},"qMsg":{}},"qColumnOrder":[0,1],"qExpansionState":[],"qDynamicScript":[],"customErrorMessage":{"calcCond":""},"columnWidths":[-1,-1],"qLayoutExclude":{"qHyperCubeDef":{"qDimensions":[],"qMeasures":[],"qInterColumnSortOrder":[],"qInitialDataFetch":[],"qReductionMode":"N","qMode":"S","qPseudoDimPos":-1,"qNoOfLeftDims":-1,"qMaxStackedCells":5000,"qCalcCond":{},"qTitle":{},"qCalcCondition":{"qCond":{},"qMsg":{}},"qColumnOrder":[],"qExpansionState":[],"qDynamicScript":[]}}},"showTitles":false,"title":"","subtitle":"","footnote":"","disableNavMenu":false,"showDetails":true,"showDetailsExpression":false,"table":{"showTitle":true,"title":"Writeback Table custom header","titleHeight":30,"titleBgColor":{"color":"#ffffff","index":"-1"},"titleColor":{"color":"#595959","index":"-1"},"titleSize":13,"titleStyle":{"bold":"bold"},"showHeader":true,"headerBgColor":"","headerColor":"","rowHeight":40,"freeze":false,"highlightedBgColor":{"color":"#ff8d24","index":"-1"},"highlightedColor":{"color":"#ffffff","index":"-1"},"editedRowBgColor":"","editedRowColor":"","showStrips":false,"stripBgColor":{"color":"#f4f4f4","index":-1},"stripFontColor":{"color":"#595959","index":-1}},"pagination":{"show":true,"showRowsPerPage":true,"rowsPerPage":10,"textColor":{"color":"#595959","index":"-1"},"activeColor":{"color":"#595959","index":"-1"},"inactiveColor":{"color":"#d3d3d3","index":"-1"},"textStyle":{},"footerHeight":40,"footerBgColor":{"color":"#ffffff","index":"-1"}},"buttons":[{"label":"Add Row","actions":[{"action":"addRow","cId":"ScdBYh"}],"badge":false,"bgColor":{"index":1,"color":"#ffffff"},"fontColor":{"index":15,"color":"#000000"},"disabledBgColor":{"color":"#d3d3d3","index":"-1"},"disabledColor":{"color":"#ffffff","index":"-1"},"fontSize":14,"showLabel":false,"iconType":"solid","iconName":"faAdd","iconPosition":"left","cId":"ZxuuLi"},{"label":"Save","actions":[{"action":"save","cId":"XRFCAg"}],"badge":true,"bgColor":{"color":"#f47907","index":"-1"},"fontColor":{"color":"#ffffff","index":"-1"},"disabledBgColor":{"color":"#d3d3d3","index":"-1"},"disabledColor":{"color":"#ffffff","index":"-1"},"fontSize":14,"showLabel":true,"iconType":"solid","iconName":"faSave","iconPosition":"left","cId":"RasYTq"}],"buttonPostion":true,"visualization":"SenseOpsWriteback","user":{"qStringExpression":{"qExpr":"=OSUser()"}},"qDimensionListDef":{"qType":"dimension","qData":{}},"qMeasureListDef":{"qType":"measure","qData":{}},"version":"June2024","extensionMeta":{"translationKey":"","icon":"table-edit","iconChar":"puzzle","isLibraryItem":true,"visible":true,"IconDefinition":{},"name":"Writeback table","description":"Users can now seamlessly write or edit data within Qlik Sense applications, text files (.csv, .txt), and database connections, facilitating a more dynamic and comprehensive data management experience.","template":"SenseOpsWriteback","iconPath":"M14.5,9 L13,9 L13,3.3 C13,3.1 12.9,3 12.7,3 L8,3 L8,1.5 C8,0.7 7.3,0 6.5,0 C5.7,0 5,0.7 5,1.5 L5,3 L0.3,3 C0.1,3 0,3.1 0,3.3 L0,9 L1.5,9 C2.3,9 3,9.7 3,10.5 C3,11.3 2.3,12 1.5,12 L0,12 L0,15.7 C0,15.9 0.1,16 0.3,16 L5,16 L5,14.5 C5,13.7 5.7,13 6.5,13 C7.3,13 8,13.7 8,14.5 L8,16 L12.7,16 C12.9,16 13,15.9 13,15.7 L13,12 L14.5,12 C15.3,12 16,11.3 16,10.5 C16,9.7 15.3,9 14.5,9 Z","isThirdParty":true,"type":"visualization","version":"June2024","author":"SenseOps","homepage":"","keywords":"qlik-sense, visualization","license":"","preview":"SenseOps.png","repository":"","dependencies":{"qlik-sense":">=3.0.x"},"bundle":{"id":"sense-ops","name":"SenseOps","description":"This is a SenseOps App Extensions"},"previewIconURL":"https://kumar-pc/extensions/SenseOpsWriteback/SenseOps.png"},"connSetup":{"uuid":"d17043fc-044a-4fde-a5e5-a3484020af28","currentKeyPath":["structure"],"destination":{"name":"destination","status":false,"destination_type":{"name":"File","id":"file"},"file":{"location":{"name":"WritebackSampleSource","id":"ddd13d4b-f0eb-4db2-953c-0d91183fe926"},"name":"1234","extension":{"name":".CSV","id":".csv"},"status":true},"database":{"server":"","db_name":"","table_name":"","status":false},"api":{"method":"GET","url":"","status":false},"operation":"Update"},"columns":{"name":"columns","status":true,"table":[{"id":"fMidPh","libraryId":"CalcMeafMidPh","type":"measure","name":"inputData","representation":"text","visibility":true,"isCustom":true,"chosen":false,"selected":false},{"id":"yydQUV","libraryId":"XsDgFT","name":"BrandBranchMonthKey","type":"field","representation":"text","visibility":true,"isCustom":false}]},"structure":[{"name":"1234","columns":[{"id":"fMidPh","libraryId":"CalcMea_gGdUMP","type":"measure","name":"inputData","representation":"text","visibility":true,"isCustom":true,"chosen":false,"selected":false},{"id":"htIQYq","libraryId":"XsDgFT","name":"BrandBranchMonthKey","type":"field","representation":"text","visibility":true,"isCustom":false,"chosen":false}],"key":"BrandBranchMonthKey"}],"actions":{"onSuccess":{},"onFailure":{}},"showAuditColumn":false}},"qChildren":[]}]}}}